spyt/__init__.py
spyt/arcadia.py
spyt/client.py
spyt/common.py
spyt/conf.py
spyt/connect.py
spyt/dependency_utils.py
spyt/enabler.py
spyt/extensions.py
spyt/launch_utils.py
spyt/spec.py
spyt/standalone.py
spyt/submit.py
spyt/types.py
spyt/utils.py
spyt/version.py
spyt/bin/driver-op-discovery.sh
spyt/bin/getGpusResources.sh
spyt/bin/job-id-discovery.sh
spyt/bin/python-binary-wrapper.sh
spyt/bin/unified-agent-spark-sensor-normalizer.py
spyt/conf/log4j.clusterLog.properties
spyt/conf/log4j.clusterLogJson.properties
spyt/conf/log4j.livy.properties
spyt/conf/log4j.properties
spyt/conf/log4j.worker.properties
spyt/conf/log4j2.clusterLog.properties
spyt/conf/log4j2.clusterLogJson.properties
spyt/conf/log4j2.properties
spyt/conf/metrics.properties
spyt/conf/spark-defaults.conf
spyt/conf/spark-env.sh
spyt/jars/annotations-1.2.12.jar
spyt/jars/cats-core_2.12-2.0.0.jar
spyt/jars/cats-macros_2.12-2.0.0.jar
spyt/jars/circe-core_2.12-0.12.3.jar
spyt/jars/circe-generic_2.12-0.12.3.jar
spyt/jars/circe-jawn_2.12-0.12.3.jar
spyt/jars/circe-numbers_2.12-0.12.3.jar
spyt/jars/circe-parser_2.12-0.12.3.jar
spyt/jars/circe-yaml_2.12-0.12.0.jar
spyt/jars/core_2.12-1.1.3.jar
spyt/jars/core_2.12-2.1.4.jar
spyt/jars/javax.servlet-api-3.1.0.jar
spyt/jars/jawn-parser_2.12-0.14.2.jar
spyt/jars/jetty-http-9.2.19.v20160908.jar
spyt/jars/jetty-io-9.2.19.v20160908.jar
spyt/jars/jetty-security-9.2.19.v20160908.jar
spyt/jars/jetty-server-9.2.19.v20160908.jar
spyt/jars/jetty-servlet-9.2.19.v20160908.jar
spyt/jars/jetty-util-9.2.19.v20160908.jar
spyt/jars/jetty-webapp-9.2.19.v20160908.jar
spyt/jars/jetty-xml-9.2.19.v20160908.jar
spyt/jars/json-smart-1.1.1.jar
spyt/jars/jsonevent-layout-1.7.jar
spyt/jars/juniversalchardet-1.0.3.jar
spyt/jars/protobuf-java-4.33.0.jar
spyt/jars/scalatra-common_2.12-2.7.0.jar
spyt/jars/scalatra_2.12-2.7.0.jar
spyt/jars/scalding-args_2.12-0.17.4.jar
spyt/jars/shapeless_2.12-2.3.7.jar
spyt/jars/skiff-1.2.12.jar
spyt/jars/snakeyaml-1.25.jar
ytsaurus_spyt-2.8.1.dist-info/METADATA
ytsaurus_spyt-2.8.1.dist-info/WHEEL
ytsaurus_spyt-2.8.1.dist-info/top_level.txt
ytsaurus_spyt-2.8.1.dist-info/RECORD
